{
  "protocol_version" : "0.0.6",
  "configuration" : {
    "version" : "(6.10.0.104) (2019-12/5d03a6fe116)",
    "tlc" : "normal",
    "sigsgev" : "altstack",
    "notifications" : "kqueue",
    "architecture" : "amd64",
    "disabled_features" : "none",
    "smallconfig" : "disabled",
    "bigarrays" : "disabled",
    "softdebug" : "enabled",
    "interpreter" : "enabled",
    "llvm_support" : "0",
    "suspend" : "hybrid"
  },
  "memory" : {
    "Resident Size" : "207151104",
    "Virtual Size" : "4643270656",
    "minor_gc_time" : "500225",
    "major_gc_time" : "409380",
    "minor_gc_count" : "3",
    "major_gc_count" : "2",
    "major_gc_time_concurrent" : "0"
 },
  "threads" : [
 {
    "is_managed" : false,
    "offset_free_hash" : "0x0",
    "offset_rich_hash" : "0x0",
    "crashed" : false,
    "native_thread_id" : "0x70000d5ae000",
    "thread_info_addr" : "0x7fd4bf81be00",
    "thread_name" : "Finalizer",
    "ctx" : {
      "IP" : "0x7fff6afbce36",
      "SP" : "0x70000d5adeb8",
      "BP" : "0x70000d5adf00"
  },
    "unmanaged_frames" : [
  {
      "is_managed" : "false",
      "native_address" : "0x1018bf346",
      "native_offset" : "0x00000"
   }
,
  {
      "is_managed" : "false",
      "native_address" : "0x101a59aa5",
      "native_offset" : "0x00000"
   }
,
  {
      "is_managed" : "false",
      "native_address" : "0x101a597d7",
      "native_offset" : "0x00000"
   }
,
  {
      "is_managed" : "false",
      "native_address" : "0x10192ace0",
      "native_offset" : "0x00000"
   }
,
  {
      "is_managed" : "false",
      "native_address" : "0x7fff6b0745fd",
      "native_offset" : "0x00000"
   }
,
  {
      "is_managed" : "false",
      "native_address" : "0x1000",
      "native_offset" : "0x00000"
   }
,
  {
      "is_managed" : "false",
      "native_address" : "0x101a5a6ed",
      "native_offset" : "0x00000"
   }
,
  {
      "is_managed" : "false",
      "native_address" : "0x7fff6b080109",
      "native_offset" : "0x00000"
   }
,
  {
      "is_managed" : "false",
      "native_address" : "0x7fff6b07bb8b",
      "native_offset" : "0x00000"
   }

  ]
 },
 {
    "is_managed" : true,
    "offset_free_hash" : "0x1979963d15",
    "offset_rich_hash" : "0x197996403d",
    "crashed" : true,
    "native_thread_id" : "0x70000dec0000",
    "thread_info_addr" : "0x7fd4be875000",
    "thread_name" : "Thread Pool Worker",
    "ctx" : {
      "IP" : "0x7fff6afc333a",
      "SP" : "0x70000debe648",
      "BP" : "0x70000debe670"
  },
    "managed_frames" : [
  {
      "is_managed" : "false",
      "native_address" : "unregistered"
   }
,
  {
      "is_managed" : "true",
      "guid" : "55ADAE45-46CD-485B-A70E-2948332EBE8C",
      "token" : "0x00000",
      "native_offset" : "0x0",
      "filename" : "mscorlib.dll",
      "sizeofimage" : "0x474000",
      "timestamp" : "0xcdf122ed",
      "il_offset" : "0x0000c"
   }
,
  {
      "is_managed" : "true",
      "guid" : "55ADAE45-46CD-485B-A70E-2948332EBE8C",
      "token" : "0x6001f8c",
      "native_offset" : "0x0",
      "filename" : "mscorlib.dll",
      "sizeofimage" : "0x474000",
      "timestamp" : "0xcdf122ed",
      "il_offset" : "0x0001a"
   }
,
  {
      "is_managed" : "true",
      "guid" : "55ADAE45-46CD-485B-A70E-2948332EBE8C",
      "token" : "0x6001f32",
      "native_offset" : "0x0",
      "filename" : "mscorlib.dll",
      "sizeofimage" : "0x474000",
      "timestamp" : "0xcdf122ed",
      "il_offset" : "0x00028"
   }
,
  {
      "is_managed" : "true",
      "guid" : "55ADAE45-46CD-485B-A70E-2948332EBE8C",
      "token" : "0x6001f30",
      "native_offset" : "0x0",
      "filename" : "mscorlib.dll",
      "sizeofimage" : "0x474000",
      "timestamp" : "0xcdf122ed",
      "il_offset" : "0x00002"
   }
,
  {
      "is_managed" : "true",
      "guid" : "0A524050-C08D-4243-8E8C-E610E157685E",
      "token" : "0x6000084",
      "native_offset" : "0x0",
      "filename" : "MonoDevelop.MSBuildBuilder.exe",
      "sizeofimage" : "0x14000",
      "timestamp" : "0xcf68e9fd",
      "il_offset" : "0x000ae"
   }
,
  {
      "is_managed" : "true",
      "guid" : "0A524050-C08D-4243-8E8C-E610E157685E",
      "token" : "0x6000083",
      "native_offset" : "0x0",
      "filename" : "MonoDevelop.MSBuildBuilder.exe",
      "sizeofimage" : "0x14000",
      "timestamp" : "0xcf68e9fd",
      "il_offset" : "0x00001"
   }
,
  {
      "is_managed" : "true",
      "guid" : "0A524050-C08D-4243-8E8C-E610E157685E",
      "token" : "0x600006a",
      "native_offset" : "0x0",
      "filename" : "MonoDevelop.MSBuildBuilder.exe",
      "sizeofimage" : "0x14000",
      "timestamp" : "0xcf68e9fd",
      "il_offset" : "0x00048"
   }
,
  {
      "is_managed" : "true",
      "guid" : "0A524050-C08D-4243-8E8C-E610E157685E",
      "token" : "0x60000a1",
      "native_offset" : "0x0",
      "filename" : "MonoDevelop.MSBuildBuilder.exe",
      "sizeofimage" : "0x14000",
      "timestamp" : "0xcf68e9fd",
      "il_offset" : "0x00001"
   }
,
  {
      "is_managed" : "true",
      "guid" : "0A524050-C08D-4243-8E8C-E610E157685E",
      "token" : "0x6000067",
      "native_offset" : "0x0",
      "filename" : "MonoDevelop.MSBuildBuilder.exe",
      "sizeofimage" : "0x14000",
      "timestamp" : "0xcf68e9fd",
      "il_offset" : "0x00001"
   }
,
  {
      "is_managed" : "true",
      "guid" : "0A524050-C08D-4243-8E8C-E610E157685E",
      "token" : "0x6000075",
      "native_offset" : "0x0",
      "filename" : "MonoDevelop.MSBuildBuilder.exe",
      "sizeofimage" : "0x14000",
      "timestamp" : "0xcf68e9fd",
      "il_offset" : "0x00057"
   }
,
  {
      "is_managed" : "true",
      "guid" : "0A524050-C08D-4243-8E8C-E610E157685E",
      "token" : "0x00000",
      "native_offset" : "0x0",
      "filename" : "MonoDevelop.MSBuildBuilder.exe",
      "sizeofimage" : "0x14000",
      "timestamp" : "0xcf68e9fd",
      "il_offset" : "0x0002a"
   }
,
  {
      "is_managed" : "false",
      "native_address" : "unregistered"
   }
,
  {
      "is_managed" : "true",
      "guid" : "55ADAE45-46CD-485B-A70E-2948332EBE8C",
      "token" : "0x00000",
      "native_offset" : "0x0",
      "filename" : "mscorlib.dll",
      "sizeofimage" : "0x474000",
      "timestamp" : "0xcdf122ed",
      "il_offset" : "0x0000c"
   }
,
  {
      "is_managed" : "true",
      "guid" : "55ADAE45-46CD-485B-A70E-2948332EBE8C",
      "token" : "0x60048d1",
      "native_offset" : "0x0",
      "filename" : "mscorlib.dll",
      "sizeofimage" : "0x474000",
      "timestamp" : "0xcdf122ed",
      "il_offset" : "0x00000"
   }
,
  {
      "is_managed" : "true",
      "guid" : "0A524050-C08D-4243-8E8C-E610E157685E",
      "token" : "0x6000039",
      "native_offset" : "0x0",
      "filename" : "MonoDevelop.MSBuildBuilder.exe",
      "sizeofimage" : "0x14000",
      "timestamp" : "0xcf68e9fd",
      "il_offset" : "0x00019"
   }
,
  {
      "is_managed" : "true",
      "guid" : "0A524050-C08D-4243-8E8C-E610E157685E",
      "token" : "0x6000169",
      "native_offset" : "0x0",
      "filename" : "MonoDevelop.MSBuildBuilder.exe",
      "sizeofimage" : "0x14000",
      "timestamp" : "0xcf68e9fd",
      "il_offset" : "0x00029"
   }
,
  {
      "is_managed" : "true",
      "guid" : "0A524050-C08D-4243-8E8C-E610E157685E",
      "token" : "0x6000184",
      "native_offset" : "0x0",
      "filename" : "MonoDevelop.MSBuildBuilder.exe",
      "sizeofimage" : "0x14000",
      "timestamp" : "0xcf68e9fd",
      "il_offset" : "0x00001"
   }
,
  {
      "is_managed" : "true",
      "guid" : "55ADAE45-46CD-485B-A70E-2948332EBE8C",
      "token" : "0x6001ece",
      "native_offset" : "0x0",
      "filename" : "mscorlib.dll",
      "sizeofimage" : "0x474000",
      "timestamp" : "0xcdf122ed",
      "il_offset" : "0x00071"
   }
,
  {
      "is_managed" : "true",
      "guid" : "55ADAE45-46CD-485B-A70E-2948332EBE8C",
      "token" : "0x6001ecc",
      "native_offset" : "0x0",
      "filename" : "mscorlib.dll",
      "sizeofimage" : "0x474000",
      "timestamp" : "0xcdf122ed",
      "il_offset" : "0x00000"
   }
,
  {
      "is_managed" : "true",
      "guid" : "55ADAE45-46CD-485B-A70E-2948332EBE8C",
      "token" : "0x6001fd9",
      "native_offset" : "0x0",
      "filename" : "mscorlib.dll",
      "sizeofimage" : "0x474000",
      "timestamp" : "0xcdf122ed",
      "il_offset" : "0x00074"
   }
,
  {
      "is_managed" : "true",
      "guid" : "55ADAE45-46CD-485B-A70E-2948332EBE8C",
      "token" : "0x6001fee",
      "native_offset" : "0x0",
      "filename" : "mscorlib.dll",
      "sizeofimage" : "0x474000",
      "timestamp" : "0xcdf122ed",
      "il_offset" : "0x00000"
   }
,
  {
      "is_managed" : "true",
      "guid" : "55ADAE45-46CD-485B-A70E-2948332EBE8C",
      "token" : "0x00000",
      "native_offset" : "0x0",
      "filename" : "mscorlib.dll",
      "sizeofimage" : "0x474000",
      "timestamp" : "0xcdf122ed",
      "il_offset" : "0x0002a"
   }

  ],
  "unmanaged_frames" : [
 {
    "is_managed" : "false",
    "native_address" : "0x1018bf346",
    "native_offset" : "0x00000"
  }
,
 {
    "is_managed" : "false",
    "native_address" : "0x101a59aa5",
    "native_offset" : "0x00000"
  }
,
 {
    "is_managed" : "false",
    "native_address" : "0x101a5a11a",
    "native_offset" : "0x00000"
  }
,
 {
    "is_managed" : "false",
    "native_address" : "0x10192bda7",
    "native_offset" : "0x00000"
  }
,
 {
    "is_managed" : "false",
    "native_address" : "0x1018c3fb5",
    "native_offset" : "0x00000"
  }
,
 {
    "is_managed" : "false",
    "native_address" : "0x10192b09f",
    "native_offset" : "0x00000"
  }
,
 {
    "is_managed" : "false",
    "native_address" : "0x7fff6b0745fd",
    "native_offset" : "0x00000"
  }
,
 {
    "is_managed" : "false",
    "native_address" : "unregistered"
  }
,
 {
    "is_managed" : "false",
    "native_address" : "0x7fff6af4a808",
    "native_offset" : "0x00000"
  }
,
 {
    "is_managed" : "false",
    "native_address" : "0x101b29397",
    "native_offset" : "0x00000"
  }
,
 {
    "is_managed" : "false",
    "native_address" : "0x101b0a27f",
    "native_offset" : "0x00000"
  }
,
 {
    "is_managed" : "false",
    "native_address" : "0x101b2971e",
    "native_offset" : "0x00000"
  }
,
 {
    "is_managed" : "false",
    "native_address" : "0x101b2989f",
    "native_offset" : "0x00000"
  }
,
 {
    "is_managed" : "false",
    "native_address" : "0x1019c6059",
    "native_offset" : "0x00000"
  }
,
 {
    "is_managed" : "false",
    "native_address" : "0x1019c65f2",
    "native_offset" : "0x00000"
  }
,
 {
    "is_managed" : "false",
    "native_address" : "0x101b176d1",
    "native_offset" : "0x00000"
  }
,
 {
    "is_managed" : "false",
    "native_address" : "0x101b17a70",
    "native_offset" : "0x00000"
  }
,
 {
    "is_managed" : "false",
    "native_address" : "0x1019c8706",
    "native_offset" : "0x00000"
  }
,
 {
    "is_managed" : "false",
    "native_address" : "0x1019ecab4",
    "native_offset" : "0x00000"
  }
,
 {
    "is_managed" : "true",
    "guid" : "55ADAE45-46CD-485B-A70E-2948332EBE8C",
    "token" : "0x00000",
    "native_offset" : "0x0",
    "filename" : "mscorlib.dll",
    "sizeofimage" : "0x474000",
    "timestamp" : "0xcdf122ed",
    "il_offset" : "0x00000"
  }
,
 {
    "is_managed" : "true",
    "guid" : "55ADAE45-46CD-485B-A70E-2948332EBE8C",
    "token" : "0x6001f8c",
    "native_offset" : "0x0",
    "filename" : "mscorlib.dll",
    "sizeofimage" : "0x474000",
    "timestamp" : "0xcdf122ed",
    "il_offset" : "0x00000"
  }
,
 {
    "is_managed" : "true",
    "guid" : "0A524050-C08D-4243-8E8C-E610E157685E",
    "token" : "0x6000083",
    "native_offset" : "0x0",
    "filename" : "MonoDevelop.MSBuildBuilder.exe",
    "sizeofimage" : "0x14000",
    "timestamp" : "0xcf68e9fd",
    "il_offset" : "0x00000"
  }
,
 {
    "is_managed" : "true",
    "guid" : "0A524050-C08D-4243-8E8C-E610E157685E",
    "token" : "0x600006a",
    "native_offset" : "0x0",
    "filename" : "MonoDevelop.MSBuildBuilder.exe",
    "sizeofimage" : "0x14000",
    "timestamp" : "0xcf68e9fd",
    "il_offset" : "0x00000"
  }
,
 {
    "is_managed" : "true",
    "guid" : "0A524050-C08D-4243-8E8C-E610E157685E",
    "token" : "0x60000a1",
    "native_offset" : "0x0",
    "filename" : "MonoDevelop.MSBuildBuilder.exe",
    "sizeofimage" : "0x14000",
    "timestamp" : "0xcf68e9fd",
    "il_offset" : "0x00000"
  }
,
 {
    "is_managed" : "true",
    "guid" : "0A524050-C08D-4243-8E8C-E610E157685E",
    "token" : "0x6000067",
    "native_offset" : "0x0",
    "filename" : "MonoDevelop.MSBuildBuilder.exe",
    "sizeofimage" : "0x14000",
    "timestamp" : "0xcf68e9fd",
    "il_offset" : "0x00000"
  }
,
 {
    "is_managed" : "true",
    "guid" : "0A524050-C08D-4243-8E8C-E610E157685E",
    "token" : "0x6000075",
    "native_offset" : "0x0",
    "filename" : "MonoDevelop.MSBuildBuilder.exe",
    "sizeofimage" : "0x14000",
    "timestamp" : "0xcf68e9fd",
    "il_offset" : "0x00000"
  }
,
 {
    "is_managed" : "true",
    "guid" : "0A524050-C08D-4243-8E8C-E610E157685E",
    "token" : "0x00000",
    "native_offset" : "0x0",
    "filename" : "MonoDevelop.MSBuildBuilder.exe",
    "sizeofimage" : "0x14000",
    "timestamp" : "0xcf68e9fd",
    "il_offset" : "0x00000"
  }
,
 {
    "is_managed" : "false",
    "native_address" : "0x101821ae2",
    "native_offset" : "0x00000"
  }
,
 {
    "is_managed" : "false",
    "native_address" : "0x101a2f967",
    "native_offset" : "0x00000"
  }
,
 {
    "is_managed" : "false",
    "native_address" : "0x101a38409",
    "native_offset" : "0x00000"
  }
,
 {
    "is_managed" : "false",
    "native_address" : "0x1019d038d",
    "native_offset" : "0x00000"
  }
,
 {
    "is_managed" : "false",
    "native_address" : "0x1019e4027",
    "native_offset" : "0x00000"
  }
,
 {
    "is_managed" : "true",
    "guid" : "55ADAE45-46CD-485B-A70E-2948332EBE8C",
    "token" : "0x00000",
    "native_offset" : "0x0",
    "filename" : "mscorlib.dll",
    "sizeofimage" : "0x474000",
    "timestamp" : "0xcdf122ed",
    "il_offset" : "0x00000"
  }
,
 {
    "is_managed" : "true",
    "guid" : "(null)",
    "token" : "0x00000",
    "native_offset" : "0x0",
    "filename" : "(null)",
    "sizeofimage" : "0x0",
    "timestamp" : "0x0",
    "il_offset" : "0x00000"
  }
,
 {
    "is_managed" : "true",
    "guid" : "55ADAE45-46CD-485B-A70E-2948332EBE8C",
    "token" : "0x60048d1",
    "native_offset" : "0x0",
    "filename" : "mscorlib.dll",
    "sizeofimage" : "0x474000",
    "timestamp" : "0xcdf122ed",
    "il_offset" : "0x00000"
  }
,
 {
    "is_managed" : "true",
    "guid" : "0A524050-C08D-4243-8E8C-E610E157685E",
    "token" : "0x6000169",
    "native_offset" : "0x0",
    "filename" : "MonoDevelop.MSBuildBuilder.exe",
    "sizeofimage" : "0x14000",
    "timestamp" : "0xcf68e9fd",
    "il_offset" : "0x00000"
  }
,
 {
    "is_managed" : "true",
    "guid" : "0A524050-C08D-4243-8E8C-E610E157685E",
    "token" : "0x6000184",
    "native_offset" : "0x0",
    "filename" : "MonoDevelop.MSBuildBuilder.exe",
    "sizeofimage" : "0x14000",
    "timestamp" : "0xcf68e9fd",
    "il_offset" : "0x00000"
  }
,
 {
    "is_managed" : "true",
    "guid" : "(null)",
    "token" : "0x00000",
    "native_offset" : "0x0",
    "filename" : "(null)",
    "sizeofimage" : "0x0",
    "timestamp" : "0x0",
    "il_offset" : "0x00000"
  }
,
 {
    "is_managed" : "true",
    "guid" : "55ADAE45-46CD-485B-A70E-2948332EBE8C",
    "token" : "0x6001ecc",
    "native_offset" : "0x0",
    "filename" : "mscorlib.dll",
    "sizeofimage" : "0x474000",
    "timestamp" : "0xcdf122ed",
    "il_offset" : "0x00000"
  }
,
 {
    "is_managed" : "true",
    "guid" : "55ADAE45-46CD-485B-A70E-2948332EBE8C",
    "token" : "0x6001fee",
    "native_offset" : "0x0",
    "filename" : "mscorlib.dll",
    "sizeofimage" : "0x474000",
    "timestamp" : "0xcdf122ed",
    "il_offset" : "0x00000"
  }
,
 {
    "is_managed" : "false",
    "native_address" : "0x101821ae2",
    "native_offset" : "0x00000"
  }
,
 {
    "is_managed" : "false",
    "native_address" : "0x101a31342",
    "native_offset" : "0x00000"
  }
,
 {
    "is_managed" : "false",
    "native_address" : "0x101a5d1c7",
    "native_offset" : "0x00000"
  }
,
 {
    "is_managed" : "false",
    "native_address" : "0x101990f88",
    "native_offset" : "0x00000"
  }
,
 {
    "is_managed" : "false",
    "native_address" : "0x101a5a6ed",
    "native_offset" : "0x00000"
  }
,
 {
    "is_managed" : "false",
    "native_address" : "0x7fff6b080109",
    "native_offset" : "0x00000"
  }
,
 {
    "is_managed" : "false",
    "native_address" : "0x7fff6b07bb8b",
    "native_offset" : "0x00000"
  }

 ]
},
{
  "is_managed" : false,
  "offset_free_hash" : "0x0",
  "offset_rich_hash" : "0x0",
  "crashed" : false,
  "native_thread_id" : "0x108070dc0",
  "thread_info_addr" : "0x7fd4be015000",
  "thread_name" : "tid_307",
  "ctx" : {
    "IP" : "0x7fff6afbf882",
    "SP" : "0x7ffeee3f0c08",
    "BP" : "0x7ffeee3f0ca0"
 },
  "unmanaged_frames" : [
 {
    "is_managed" : "false",
    "native_address" : "0x1018bf346",
    "native_offset" : "0x00000"
  }
,
 {
    "is_managed" : "false",
    "native_address" : "0x101a59aa5",
    "native_offset" : "0x00000"
  }
,
 {
    "is_managed" : "false",
    "native_address" : "0x101a597d7",
    "native_offset" : "0x00000"
  }
,
 {
    "is_managed" : "false",
    "native_address" : "0x10192ace0",
    "native_offset" : "0x00000"
  }
,
 {
    "is_managed" : "false",
    "native_address" : "0x7fff6b0745fd",
    "native_offset" : "0x00000"
  }
,
 {
    "is_managed" : "false",
    "native_address" : "0x7ffeee3f08f8",
    "native_offset" : "0x00000"
  }
,
 {
    "is_managed" : "false",
    "native_address" : "0x101b06430",
    "native_offset" : "0x00000"
  }
,
 {
    "is_managed" : "false",
    "native_address" : "0x101b1e401",
    "native_offset" : "0x00000"
  }
,
 {
    "is_managed" : "false",
    "native_address" : "0x101a569e4",
    "native_offset" : "0x00000"
  }
,
 {
    "is_managed" : "false",
    "native_address" : "0x101a567ea",
    "native_offset" : "0x00000"
  }
,
 {
    "is_managed" : "false",
    "native_address" : "0x10188530a",
    "native_offset" : "0x00000"
  }
,
 {
    "is_managed" : "false",
    "native_address" : "0x101810e49",
    "native_offset" : "0x00000"
  }
,
 {
    "is_managed" : "false",
    "native_address" : "0x7fff6ae7bcc9",
    "native_offset" : "0x00000"
  }
,
 {
    "is_managed" : "false",
    "native_address" : "0x5",
    "native_offset" : "0x00000"
  }

 ]
}
]
}